mycalc/calculator.py
oss20230411-1.0.1.dist-info/METADATA
oss20230411-1.0.1.dist-info/WHEEL
oss20230411-1.0.1.dist-info/top_level.txt
oss20230411-1.0.1.dist-info/RECORD
