Metadata-Version: 2.1
Name: oss20230411
Version: 1.0.1
Summary: nice calc
Home-page: https://github.com/jieun53/calc0001.git
Download-URL: https://github.com/jieun53/calc0001/releases/tag/v0.0.1
Author: jieunchoi
License: UNKNOWN
Platform: UNKNOWN
Classifier: Programming Language :: Python :: 3
